<?xml version="1.0" encoding="UTF-8"?>
<odoo>
    <data>

        <record id="utm_website_crm_lead_form" model="ir.ui.view">
            <field name="name">utm_website_crm_lead_form</field>
            <field name="model">crm.lead</field>
            <field name="inherit_id" ref="crm.crm_case_form_view_oppor"/>
            <field name="arch" type="xml">
                <field name="source_id" position="after">	    	
                    <field name="utm_website_id"/>
    	       </field>                           
            </field>
        </record>

    </data>
</odoo>
